litellm_impacts/__init__.py
litellm_impacts/callback.py
litellm_impacts/py.typed
litellm_impacts-0.1.0.dist-info/METADATA
litellm_impacts-0.1.0.dist-info/WHEEL
litellm_impacts-0.1.0.dist-info/licenses/LICENSE
litellm_impacts-0.1.0.dist-info/RECORD
