Metadata-Version: 2.4
Name: litellm-impacts
Version: 0.1.0
Summary: Environmental impact metrics callback for LiteLLM
Project-URL: Homepage, https://github.com/YOUR_USERNAME/litellm-impacts
Project-URL: Repository, https://github.com/YOUR_USERNAME/litellm-impacts
Project-URL: Issues, https://github.com/YOUR_USERNAME/litellm-impacts/issues
Author: Elliot
License-Expression: MIT
License-File: LICENSE
Keywords: carbon,litellm,llm,metrics,prometheus,sustainability
Classifier: Development Status :: 3 - Alpha
Classifier: Intended Audience :: Developers
Classifier: License :: OSI Approved :: MIT License
Classifier: Programming Language :: Python :: 3
Classifier: Programming Language :: Python :: 3.10
Classifier: Programming Language :: Python :: 3.11
Classifier: Programming Language :: Python :: 3.12
Classifier: Programming Language :: Python :: 3.13
Classifier: Topic :: Scientific/Engineering
Classifier: Topic :: System :: Monitoring
Requires-Python: >=3.10
Requires-Dist: ecologits>=0.7.0
Requires-Dist: litellm>=1.0.0
Requires-Dist: prometheus-client>=0.20.0
